difflume/__init__.py
difflume/__main__.py
difflume/diffapp/__init__.py
difflume/diffapp/differ.py
difflume/diffapp/modules.py
difflume/http/__init__.py
difflume/http/url.py
difflume/main.py
difflume/py.typed
difflume/tui/__init__.py
difflume/tui/app.py
difflume/tui/css/main.tcss
difflume/tui/help.md
difflume/tui/modals.py
difflume/tui/screens.py
difflume/tui/widgets.py
difflume-0.6.0.dist-info/LICENSE
difflume-0.6.0.dist-info/METADATA
difflume-0.6.0.dist-info/WHEEL
difflume-0.6.0.dist-info/entry_points.txt
difflume-0.6.0.dist-info/RECORD
