Metadata-Version: 2.1
Name: difflume
Version: 0.6.0
Summary: TUI app for viewing deltas between text files
Home-page: https://github.com/yakimka/DiffLume
License: MIT
Keywords: diff,tui,text,textual,terminal
Author: yakimka
Requires-Python: >=3.10,<4.0
Classifier: Development Status :: 5 - Production/Stable
Classifier: Intended Audience :: Developers
Classifier: Intended Audience :: System Administrators
Classifier: License :: OSI Approved :: MIT License
Classifier: Operating System :: OS Independent
Classifier: Programming Language :: Python :: 3
Classifier: Programming Language :: Python :: 3.10
Classifier: Programming Language :: Python :: 3.11
Classifier: Topic :: Utilities
Requires-Dist: httpx (>=0.24.1,<0.25.0)
Requires-Dist: textual (>=0.35.1,<0.37.0)
Project-URL: Repository, https://github.com/yakimka/DiffLume
